Workbook

Sheet Financial Data
A1: Item | B1: 2025 | C1: 2024 | D1: reference page | E1: remarks
A2: Non Current Assets | B2: 143782 | C2: 118422 | D2: 64
A3: Current Assets | B3: 24579 | C3: 22554 | D3: 64
A4: Current Liablities | B4: 32554 | C4: 31554 | D4: 64
A5: Total Assets | B5: 168361 | C5: 140976 | D5: 64
A6: Non-Current Liablities | B6: 114749 | C6: 100193 | D6: 64
A7: Current Liabilities | B7: 32643 | C7: 31544 | D7: 64
A8: Total Liabilities | B8: =B6+B7 -> 147392 | C8: =C6+C7 -> 131737 | D8: 64
A9: Common Equity | B9: 37107 | C9: 32764
A10: Total Equity | B10: 20969 | C10: 9239 | D10: 64
A11: Revenue | B11: 57399 | C11: 52961 | D11: ='Financial Data'!B137 -> 0
A12: Total Operating Expenses | B12: 39721 | C12: 37608 | D12: 65
A13: Costs of Goods Sold or Costs of Revenue | B13: 16929 | C13: 15147
A14: Gross Profit | B14: =B11-B13 -> 40470 | C14: =C11-C13 -> 37814 | D14: https://www.macrotrends.net/stocks/charts/ORCL/oracle/gross-margin
A15: Operating Expenses | B15: 22792 | C15: 22461
A16: Net Operating Income | B16: =B14-B15 -> 17678 | C16: =C14-C15 -> 15353 | D16: 65
A17: Interest Expense | B17: 978 | C17: 878
A18: Net Income | B18: 12443 | C18: 10467 | D18: 65
A19: Inventory | B19: 303 | C19: 334
A20: Accounts Receivable | B20: 835 | C20: 821
A21: Shares Outstanding | B21: 2807 | C21: 2755
A22: Shares Outstanding (Basic) | B22: 2789 | C22: 2744
A23: Shares Outstanding (Diluted) | B23: 2866 | C23: 2823
A24: Par Value per Share | B24: 0.01 | C24: 0.01
A25: Market Price Per Share (Offically used as of November of prior year) | B25: 116.21 | C25: 117.23
A27: Market Price Per Share ( as of 15.11.2025)
A28: Earnings per Share (Basic) | B28: =B18/B21 -> 4.4328465 | C28: =C18/C21 -> 3.799274
A29: Earnings per Share (Diluted) | B29: =B18/B23 -> 4.3415911 | C29: =C18/C23 -> 3.7077577
A30: Market Cap. | B30: 305,8 | C30: 186,2
A31: Book Value per Share | B31: 7.4 | C31: 3.3 | E31: dividing total equity by basic shares outstanding would give out
A32: Book Value per Share (Basic) (Calculated) | B32: =B10/B22 -> 7.5184654 | C32: =C10/C22 -> 3.3669825
A33: Book Value per Share (Diluted) (Calculated) | B33: =B10/B23 -> 7.3164689 | C33: =C10/C23 -> 3.2727595
A34: Average Book Value | B34: =AVERAGE(B32:B33) -> 7.4174672 | C34: =AVERAGE(C32:C33) -> 3.319871 | E34: all numbers are in millions, and period is used as decimal separator
A37: *

Sheet Ratio Analysis
A1: Type of Ratio | B1: Name | C1: Formula | D1: Result for 2025 | E1: Result for 2024
A2: Liquidy | B2: Current Ratio | C2: Current Assets / Current Liablities | D2: ='Financial Data'!B3/'Financial Data'!B4 -> 0.75502242 | E2: ='Financial Data'!C3/'Financial Data'!C4 -> 0.71477467
B3: Quick Acidity Ratio | C3: (Current Assets - Inventory) / Current Liabilities | D3: =('Financial Data'!B3 - 'Financial Data'!B19) / 'Financial Data'!B7 -> 0.74368165 | E3: =('Financial Data'!C3 - 'Financial Data'!C19) / 'Financial Data'!C7 -> 0.70441288
B4: Average Collection Period | C4: 365 * Accounts Receivable / Annual Credit Sales
B5: Accounts Receivable Turnover | C5: Annual Credit Sales / Accounts Receivable
B6: Inventory Turnover | C6: Costs of Goods Sold / Inventory | D6: ='Financial Data'!B13/'Financial Data'!B19 -> 55.871287 | E6: ='Financial Data'!C13/'Financial Data'!C19 -> 45.350299
A7: Capital Structure | B7: Debt Ratio | C7: Total Debt / Total Assets | D7: ='Financial Data'!B8/'Financial Data'!B5 -> 0.87545215 | E7: ='Financial Data'!C8/'Financial Data'!C5 -> 0.93446402
B8: Times Interest Earned | C8: Net Operational Income / Interest Expense | D8: ='Financial Data'!B16/'Financial Data'!B17 -> 18.075665 | E8: ='Financial Data'!C16/'Financial Data'!C17 -> 17.486333
A9: Asset Management Efficiency Ratios | B9: Total Asset Turnover | C9: Sales / Total Assets | D9: ='Financial Data'!B11/'Financial Data'!B5 -> 0.34092812 | E9: ='Financial Data'!C11/'Financial Data'!C5 -> 0.37567387
B10: Fixed Asset Turnover | C10: Sales / Net Plant and Equipment
A11: Profitability Ratios | B11: Gross Profit Margin | C11: Gross Profits / Sales | D11: ='Financial Data'!B14/'Financial Data'!B11 -> 0.70506455 | E11: ='Financial Data'!C14/'Financial Data'!C11 -> 0.71399709
B12: Net Profit Margin | C12: Net Income / Sales | D12: ='Financial Data'!B18/'Financial Data'!B11 -> 0.21678078 | E12: ='Financial Data'!C18/'Financial Data'!C11 -> 0.197636
B13: Operating Profit Margin | C13: Net Operating Income / Sales | D13: ='Financial Data'!B16/'Financial Data'!B11 -> 0.30798446 | E13: ='Financial Data'!C16/'Financial Data'!C11 -> 0.28989256
B14: Operating Return on Assets | C14: Net Operating Income / Total Assets | D14: ='Financial Data'!B16/'Financial Data'!B5 -> 0.10500056 | E14: ='Financial Data'!C16/'Financial Data'!C5 -> 0.10890506
B15: Return on Equity | C15: Net Income / Common Equity | D15: ='Financial Data'!B18/'Financial Data'!B9 -> 0.33532757 | E15: ='Financial Data'!C18/'Financial Data'!C9 -> 0.31946649
A16: Market Value Ratios | B16: Price Earning Ratio | C16: Market Price per Share / Earnings per Share | D16: ='Financial Data'!B25/'Financial Data'!B29 -> 26.766685 | E16: ='Financial Data'!C25/'Financial Data'!C29 -> 31.617492
B17: Market-to Book Ratio | C17: Market Price per Share / Book Value per Share | D17: ='Financial Data'!B25/'Financial Data'!B31 -> 15.704054 | E17: ='Financial Data'!C25/'Financial Data'!C31 -> 35.524242
A19: Earnings Per Share | B19: Basic EPS
B20: Diluted EPS

Sheet TBD - Du-Pont Analysis

Sheet TBD - Financial Analysis
