Workbook

Sheet Financial Data
A1: Item | B1: 2024 | C1: 2025
A2: Current Assets | B2: 159734 | C2: 191131
A3: Current Liabilities | B3: 125286 | C3: 141218
A4: Total Assets | B4: 512163 | C4: 619003
A5: Total Liabilities | B5: 243686 | C5: 275524
A6: Total Equity | B6: 268477 | C6: 343479
A7: Revenue | B7: 245122 | C7: 281724
A8: Cost of Goods sold | B8: 74144 | C8: 87831
A9: Net income | B9: 88136 | C9: 101832
A10: inventroy | B10: 1284 | C10: 309
A11: Acount Receivable | B11: 7191 | C11: 10581
A12: Shares outstanding | B12: 7.468 | C12: 7.465
A13: Market Price per share | B13: 419.2 | C13: 496.82

Sheet Ratio Analysis
A1: Category | B1: Ratio | C1: Formula | D1: 2024 | E1: In percent % | F1: 2025 | G1: In Percent
A2: Liquidity Ratio | B2: Current Ration | C2: Current Assets / Current Liabilities | D2: ='Financial Data'!B2/'Financial Data'!B3 -> 1.2749549 | E2: ='Financial Data'!C2/'Financial Data'!C3 -> 1.3534464 | F2: ='Financial Data'!C2/'Financial Data'!C3 -> 1.3534464 | G2: =F2 -> 1.3534464
B3: Quick Ratio | C3: (Current Assets - Inventory) / Current Liabilities | D3: =('Financial Data'!B2-'Financial Data'!B10)/'Financial Data'!B3 -> 1.2647064 | E3: =('Financial Data'!C2-'Financial Data'!C10)/'Financial Data'!C3 -> 1.3512583 | F3: =('Financial Data'!C2-'Financial Data'!C10)/'Financial Data'!C3 -> 1.3512583 | G3: =F3 -> 1.3512583
A4: Leverage Ratio | B4: Debt-to-Equity | C4: Total Liabilities / Total Equity | D4: ='Financial Data'!B5/'Financial Data'!B6 -> 0.90766062 | E4: ='Financial Data'!C5/'Financial Data'!C6 -> 0.80215675 | F4: ='Financial Data'!C5/'Financial Data'!C6 -> 0.80215675 | G4: =F4 -> 0.80215675
B5: Debt Ratio | C5: Total Liabilities / Total Assets | D5: ='Financial Data'!B5/'Financial Data'!B4 -> 0.47579774 | E5: ='Financial Data'!C5/'Financial Data'!C4 -> 0.44510931 | F5: ='Financial Data'!C5/'Financial Data'!C4 -> 0.44510931 | G5: =F5 -> 0.44510931
A6: Efficiency Ratios | B6: Asset Turnover | C6: Revenue / Total Assets | D6: ='Financial Data'!B7/'Financial Data'!B4 -> 0.47860154 | E6: ='Financial Data'!C7/'Financial Data'!C4 -> 0.45512542 | F6: ='Financial Data'!C7/'Financial Data'!C4 -> 0.45512542 | G6: =F6 -> 0.45512542
B7: Receivables Turnover | C7: Revenue / Accounts Receivable | D7: ='Financial Data'!B7/'Financial Data'!B11 -> 34.087331 | E7: ='Financial Data'!C7/'Financial Data'!C11 -> 26.625461 | F7: ='Financial Data'!C7/'Financial Data'!C11 -> 26.625461 | G7: =F7 -> 26.625461
A8: Profitability Ratios | B8: Net Profit Margin | C8: Net Income / Revenue | D8: ='Financial Data'!B9/'Financial Data'!B7 -> 0.35955973 | E8: ='Financial Data'!C9/'Financial Data'!C7 -> 0.36146015 | F8: ='Financial Data'!C9/'Financial Data'!C7 -> 0.36146015 | G8: =F8 -> 0.36146015
B9: Return on Equity (ROE) | C9: Net Income / Total Equity | D9: ='Financial Data'!B9/'Financial Data'!B6 -> 0.32828138 | E9: ='Financial Data'!C9/'Financial Data'!C6 -> 0.29647227 | F9: ='Financial Data'!C9/'Financial Data'!C6 -> 0.29647227 | G9: =F9 -> 0.29647227
A10: Market Value Ratios | B10: Earnings Per Share (EPS) | C10: Net Income / Shares Outstanding | D10: ='Financial Data'!B9/'Financial Data'!B12 -> 11801.821 | E10: 0.118 | F10: ='Financial Data'!C9/'Financial Data'!C12 -> 13641.259 | G10: 13.44
B11: Price-to-Earnings (P/E) | C11: Market Price per Share / EPS | D11: ='Financial Data'!B13/'Financial Data'!B12 -> 56.132833 | E11: 56.13 | F11: ='Financial Data'!C13/'Financial Data'!C12 -> 66.553248 | G11: 66.55

Sheet Charts 
